certbot_dns_nicru/__init__.py
certbot_dns_nicru/dns_nicru.py
certbot_dns_nicru-1.0.3.dist-info/LICENSE
certbot_dns_nicru-1.0.3.dist-info/METADATA
certbot_dns_nicru-1.0.3.dist-info/WHEEL
certbot_dns_nicru-1.0.3.dist-info/entry_points.txt
certbot_dns_nicru-1.0.3.dist-info/top_level.txt
certbot_dns_nicru-1.0.3.dist-info/RECORD
