Metadata-Version: 2.2
Name: certbot_dns_nicru
Version: 1.0.3
Summary: This plugin for certbot, configures a DNS TXT record to respond to a dns-01 challenge using the nic.ru Remote REST API.
Home-page: https://github.com/shizacat/certbot-dns-nicru
Author: Alexey Matveev
Classifier: Development Status :: 3 - Alpha
Classifier: Environment :: Plugins
Classifier: Intended Audience :: System Administrators
Classifier: License :: OSI Approved :: Apache Software License
Classifier: Operating System :: POSIX :: Linux
Classifier: Programming Language :: Python
Classifier: Programming Language :: Python :: 3
Classifier: Programming Language :: Python :: 3.8
Classifier: Topic :: Internet :: WWW/HTTP
Classifier: Topic :: Security
Classifier: Topic :: System :: Installation/Setup
Classifier: Topic :: System :: Networking
Classifier: Topic :: System :: Systems Administration
Classifier: Topic :: Utilities
Requires-Python: >=3.8
License-File: LICENSE
Requires-Dist: acme>=0.29.0
Requires-Dist: certbot>=0.34.0
Requires-Dist: setuptools
Requires-Dist: requests
Requires-Dist: zope.interface
Requires-Dist: sh-nic-api>=1.0.3
